setup.py
probability_distribution_bi_norm/Binomialdistribution.py
probability_distribution_bi_norm/Gaussiandistribution.py
probability_distribution_bi_norm/Generaldistribution.py
probability_distribution_bi_norm/__init__.py
probability_distribution_bi_norm/setup.py
probability_distribution_bi_norm.egg-info/PKG-INFO
probability_distribution_bi_norm.egg-info/SOURCES.txt
probability_distribution_bi_norm.egg-info/dependency_links.txt
probability_distribution_bi_norm.egg-info/not-zip-safe
probability_distribution_bi_norm.egg-info/top_level.txt