Metadata-Version: 1.0
Name: probability-distribution-bi-norm
Version: 0.4
Summary: Gaussian and Binomial distributions
Home-page: UNKNOWN
Author: Zainab Ayodimeji
Author-email: zayodimeji@gmail.com
License: UNKNOWN
Platform: UNKNOWN
